netlist/__init__.py
netlist-0.1.0.dist-info/WHEEL
netlist-0.1.0.dist-info/METADATA
netlist-0.1.0.dist-info/RECORD
