Metadata-Version: 2.1
Name: netlist
Version: 0.1.0
Summary: Circuit Netlist Generation and Parsing
Author: Dan Fritchman
Author-email: dan@fritch.mn
Requires-Python: >=3.8,<4.0
Classifier: Programming Language :: Python :: 3
Classifier: Programming Language :: Python :: 3.8
Classifier: Programming Language :: Python :: 3.9
